harishspider
