Metadata-Version: 1.0
Name: harishspider
Version: 1.1
Summary: Harish Spider will enter your domain and scan every page of your website, extracting all emails in that page.
Home-page: http://github.com/harish121436
Author: Vadde Harish
Author-email: mahadevendra7@gmail.com
License: HarishVadde
Platform: UNKNOWN
